{
    "_date": "2023-07-02 22:12:00",
    "_total": 32678,
    "_total_diff": 105,
    "alioth": 251,
    "alioth_diff": 0,
    "andromeda": 122,
    "andromeda_diff": 1,
    "apollo": 281,
    "apollo_diff": 0,
    "barbet": 43,
    "barbet_diff": 0,
    "blueline": 1285,
    "blueline_diff": 2,
    "bramble": 30,
    "bramble_diff": 0,
    "crosshatch": 509,
    "crosshatch_diff": 0,
    "crownlte": 62,
    "crownlte_diff": 0,
    "davinci": 501,
    "davinci_diff": 1,
    "enchilada": 361,
    "enchilada_diff": 0,
    "ginkgo": 0,
    "ginkgo_diff": 0,
    "jasmine_sprout": 5176,
    "jasmine_sprout_diff": 28,
    "lavender": 578,
    "lavender_diff": 1,
    "lemonadep": 417,
    "lemonadep_diff": 0,
    "miatoll": 7668,
    "miatoll_diff": 3,
    "mido": 373,
    "mido_diff": 2,
    "redfin": 65,
    "redfin_diff": 0,
    "renoir": 250,
    "renoir_diff": 1,
    "star2lte": 73,
    "star2lte_diff": 0,
    "starlte": 64,
    "starlte_diff": 0,
    "surya": 3738,
    "surya_diff": 10,
    "taimen": 182,
    "taimen_diff": 0,
    "umi": 5379,
    "umi_diff": 43,
    "walleye": 93,
    "walleye_diff": 0,
    "wayne": 4843,
    "wayne_diff": 13,
    "whyred": 334,
    "whyred_diff": 0
}