{
    "_date": "2023-10-21 22:11:00",
    "_total": 42321,
    "_total_diff": 87,
    "alioth": 266,
    "alioth_diff": 0,
    "andromeda": 148,
    "andromeda_diff": 0,
    "apollo": 317,
    "apollo_diff": 0,
    "barbet": 68,
    "barbet_diff": 0,
    "blueline": 1583,
    "blueline_diff": 1,
    "bramble": 62,
    "bramble_diff": 0,
    "crosshatch": 610,
    "crosshatch_diff": 0,
    "crownlte": 78,
    "crownlte_diff": 0,
    "cupid": 318,
    "cupid_diff": 1,
    "davinci": 566,
    "davinci_diff": 0,
    "enchilada": 394,
    "enchilada_diff": 0,
    "ginkgo": 0,
    "ginkgo_diff": 0,
    "haydn": 0,
    "haydn_diff": 0,
    "jasmine_sprout": 6044,
    "jasmine_sprout_diff": 9,
    "lavender": 717,
    "lavender_diff": 4,
    "lemonadep": 434,
    "lemonadep_diff": 2,
    "miatoll": 10037,
    "miatoll_diff": 36,
    "mido": 438,
    "mido_diff": 1,
    "redfin": 86,
    "redfin_diff": 0,
    "renoir": 695,
    "renoir_diff": 1,
    "star2lte": 109,
    "star2lte_diff": 0,
    "starlte": 85,
    "starlte_diff": 0,
    "surya": 4032,
    "surya_diff": 1,
    "taimen": 222,
    "taimen_diff": 0,
    "umi": 7600,
    "umi_diff": 22,
    "walleye": 137,
    "walleye_diff": 0,
    "wayne": 6041,
    "wayne_diff": 5,
    "whyred": 434,
    "whyred_diff": 1,
    "zeus": 800,
    "zeus_diff": 3
}