{
    "_date": "2023-02-02 21:14:00",
    "alioth": 423,
    "alioth_diff": 1,
    "apollo": 163,
    "apollo_diff": 5,
    "crownlte": 0,
    "crownlte_diff": 0,
    "enchilada": 537,
    "enchilada_diff": 1,
    "ginkgo": 0,
    "ginkgo_diff": 0,
    "jasmine_sprout": 3203,
    "jasmine_sprout_diff": 26,
    "lemonadep": 1273,
    "lemonadep_diff": 1,
    "miatoll": 770,
    "miatoll_diff": 16,
    "renoir": 1491,
    "renoir_diff": 8,
    "star2lte": 0,
    "star2lte_diff": 0,
    "starlte": 0,
    "starlte_diff": 0,
    "surya": 2659,
    "surya_diff": 43,
    "umi": 3649,
    "umi_diff": 25,
    "wayne": 2153,
    "wayne_diff": 26
}